livekit/plugins/google/__init__.py
livekit/plugins/google/llm.py
livekit/plugins/google/log.py
livekit/plugins/google/models.py
livekit/plugins/google/py.typed
livekit/plugins/google/stt.py
livekit/plugins/google/tools.py
livekit/plugins/google/tts.py
livekit/plugins/google/utils.py
livekit/plugins/google/version.py
livekit/plugins/google/beta/__init__.py
livekit/plugins/google/beta/gemini_tts.py
livekit/plugins/google/realtime/__init__.py
livekit/plugins/google/realtime/api_proto.py
livekit/plugins/google/realtime/realtime_api.py
livekit_plugins_google-1.3.8.dist-info/METADATA
livekit_plugins_google-1.3.8.dist-info/WHEEL
livekit_plugins_google-1.3.8.dist-info/RECORD
