Metadata-Version: 2.4
Name: livekit-plugins-google
Version: 1.3.8
Summary: Agent Framework plugin for services from Google Cloud
Project-URL: Documentation, https://docs.livekit.io
Project-URL: Website, https://livekit.io/
Project-URL: Source, https://github.com/livekit/agents
Author: LiveKit
License-Expression: Apache-2.0
Keywords: ai,audio,gemini,google,livekit,realtime,video,voice
Classifier: Intended Audience :: Developers
Classifier: License :: OSI Approved :: Apache Software License
Classifier: Programming Language :: Python :: 3
Classifier: Programming Language :: Python :: 3 :: Only
Classifier: Programming Language :: Python :: 3.9
Classifier: Programming Language :: Python :: 3.10
Classifier: Topic :: Multimedia :: Sound/Audio
Classifier: Topic :: Multimedia :: Video
Classifier: Topic :: Scientific/Engineering :: Artificial Intelligence
Requires-Python: >=3.10
Requires-Dist: google-auth<3,>=2
Requires-Dist: google-cloud-speech<3,>=2
Requires-Dist: google-cloud-texttospeech<3,>=2.32
Requires-Dist: google-genai>=1.55; python_version >= '3.10'
Requires-Dist: livekit-agents>=1.3.6
